MyDateTimeLib/__init__.py
MyDateTimeLib/myfunction.py
MyDateTimeLib/test_myfunctions.py
MyDateTimeLib-0.1.2.dist-info/METADATA
MyDateTimeLib-0.1.2.dist-info/WHEEL
MyDateTimeLib-0.1.2.dist-info/top_level.txt
MyDateTimeLib-0.1.2.dist-info/RECORD
